{
  "project_info": {
    "project_number": "608888812672",
    "firebase_url": "https://passremo-0101.firebaseio.com",
    "project_id": "passremo-0101",
    "storage_bucket": "passremo-0101.appspot.com"
  },
  "client": [
    {
      "client_info": {
        "mobilesdk_app_id": "1:608888812672:android:20fcc716f889819b",
        "android_client_info": {
          "package_name": "com.kablanfatih.passremo"
        }
      },
      "oauth_client": [
        {
          "client_id": "608888812672-bki5jjn07ctarr1voc1217b1plu9q9rf.apps.googleusercontent.com",
          "client_type": 3
        }
      ],
      "api_key": [
        {
          "current_key": "AIzaSyA59Etf1Ic1F9RD7xY8aurPIEi6vDcOf5M"
        }
      ],
      "services": {
        "analytics_service": {
          "status": 1
        },
        "appinvite_service": {
          "status": 1,
          "other_platform_oauth_client": []
        },
        "ads_service": {
          "status": 2
        }
      }
    }
  ],
  "configuration_version": "1"
}